src/binaryconv/__init__.py
src/binaryconv/convertbin.py
binaryconv_dev01111-0.0.1.dist-info/METADATA
binaryconv_dev01111-0.0.1.dist-info/WHEEL
binaryconv_dev01111-0.0.1.dist-info/licenses/LICENSE
binaryconv_dev01111-0.0.1.dist-info/RECORD
