Metadata-Version: 2.1
Name: binaryconv_dev01111
Version: 0.0.1
Summary: Binary converter for Python
Project-URL: GitHub, https://github.com/Buggem/binaryconv
Project-URL: Bugs and Glitches, https://github.com/Buggem/binaryconv/issues
Project-URL: Other Fork, https://github.com/dev01111/binaryconv_dev01111
Author: Buggem and dev01111
License: Copyright (c) 2022 Max Parry
Classifier: License :: OSI Approved :: MIT License
Classifier: Operating System :: OS Independent
Classifier: Programming Language :: Python :: 3
Requires-Python: >=3.5
